[
  {
    "file": "media/VITRAUX-NOTRE-DAME-1-6-JEAN-LOUIS-GARNELL-ADAGP-2024.jpg",
    "title": "Vitraux Notre-Dame",
    "date": "2024",
    "dimensions_physical": null,
    "dimensions_pixels": {
      "width": 1000,
      "height": 281
    },
    "series": ""
  },
  {
    "file": "media/VITRAIL-NOTRE-DAME-1.jpg",
    "title": "Vitrail Notre-Dame #1",
    "date": "2024",
    "dimensions_physical": "65 x 50 cm",
    "dimensions_pixels": {
      "width": 1000,
      "height": 281
    },
    "series": ""
  },
  {
    "file": "media/VITRAIL-NOTRE-DAME-2.jpg",
    "title": "Vitrail Notre-Dame #2",
    "date": "2024",
    "dimensions_physical": "65 x 50 cm",
    "dimensions_pixels": {
      "width": 1000,
      "height": 281
    },
    "series": ""
  },
  {
    "file": "media/VITRAIL-NOTRE-DAME-3.jpg",
    "title": "Vitrail Notre-Dame #3",
    "date": "2024",
    "dimensions_physical": "65 x 50 cm",
    "dimensions_pixels": {
      "width": 1000,
      "height": 281
    },
    "series": ""
  },
  {
    "file": "media/VITRAIL-NOTRE-DAME-4.jpg",
    "title": "Vitrail Notre-Dame #4",
    "date": "2024",
    "dimensions_physical": "65 x 50 cm",
    "dimensions_pixels": {
      "width": 1000,
      "height": 281
    },
    "series": ""
  },
  {
    "file": "media/VITRAIL-NOTRE-DAME-5.jpg",
    "title": "Vitrail Notre-Dame #5",
    "date": "2024",
    "dimensions_physical": "65 x 50 cm",
    "dimensions_pixels": {
      "width": 1000,
      "height": 281
    },
    "series": ""
  },
  {
    "file": "media/VITRAIL-NOTRE-DAME-6.jpg",
    "title": "Vitrail Notre-Dame #6",
    "date": "2024",
    "dimensions_physical": "65 x 50 cm",
    "dimensions_pixels": {
      "width": 1000,
      "height": 281
    },
    "series": ""
  }
]