[
  {
    "file": "media/chutes-1.jpg",
    "title": "CHUTES #1",
    "date": "2022",
    "dimensions_physical": "60 × 85 cm",
    "dimensions_pixels": {
      "width": 800,
      "height": 565
    },
    "series": ""
  },
  {
    "file": "media/chutes-2.jpg",
    "title": "CHUTES #2",
    "date": "2022",
    "dimensions_physical": "60 × 85 cm",
    "dimensions_pixels": {
      "width": 800,
      "height": 565
    },
    "series": ""
  },
  {
    "file": "media/chutes-3.jpg",
    "title": "CHUTES #3",
    "date": "2022",
    "dimensions_physical": "60 × 85 cm",
    "dimensions_pixels": {
      "width": 800,
      "height": 565
    },
    "series": ""
  },
  {
    "file": "media/chutes-4.jpg",
    "title": "CHUTES #4",
    "date": "2022",
    "dimensions_physical": "60 × 85 cm",
    "dimensions_pixels": {
      "width": 800,
      "height": 565
    },
    "series": ""
  },
  {
    "file": "media/chutes-5.jpg",
    "title": "CHUTES #5",
    "date": "2022",
    "dimensions_physical": "60 × 85 cm",
    "dimensions_pixels": {
      "width": 800,
      "height": 565
    },
    "series": ""
  },
  {
    "file": "media/chutes-6.jpg",
    "title": "CHUTES #6",
    "date": "2022",
    "dimensions_physical": "60 × 85 cm",
    "dimensions_pixels": {
      "width": 800,
      "height": 565
    },
    "series": ""
  },
  {
    "file": "media/chutes-7.jpg",
    "title": "CHUTES #7",
    "date": "2022",
    "dimensions_physical": "60 × 85 cm",
    "dimensions_pixels": {
      "width": 800,
      "height": 565
    },
    "series": ""
  },
  {
    "file": "media/chutes-8.jpg",
    "title": "CHUTES #8",
    "date": "2022",
    "dimensions_physical": "60 × 85 cm",
    "dimensions_pixels": {
      "width": 800,
      "height": 565
    },
    "series": ""
  },
  {
    "file": "media/chutes-9.jpg",
    "title": "CHUTES #9",
    "date": "2022",
    "dimensions_physical": "60 × 85 cm",
    "dimensions_pixels": {
      "width": 800,
      "height": 565
    },
    "series": ""
  },
  {
    "file": "media/chutes-10.jpg",
    "title": "CHUTES #10",
    "date": "2022",
    "dimensions_physical": "60 × 85 cm",
    "dimensions_pixels": {
      "width": 800,
      "height": 565
    },
    "series": ""
  },
  {
    "file": "media/chutes-11.jpg",
    "title": "CHUTES #11",
    "date": "2022",
    "dimensions_physical": "60 × 85 cm",
    "dimensions_pixels": {
      "width": 800,
      "height": 565
    },
    "series": ""
  },
  {
    "file": "media/chutes-12.jpg",
    "title": "CHUTES #12",
    "date": "2022",
    "dimensions_physical": "60 × 85 cm",
    "dimensions_pixels": {
      "width": 800,
      "height": 565
    },
    "series": ""
  },
  {
    "file": "media/chutes-13.jpg",
    "title": "CHUTES #13",
    "date": "2022",
    "dimensions_physical": "60 × 85 cm",
    "dimensions_pixels": {
      "width": 800,
      "height": 565
    },
    "series": ""
  },
  {
    "file": "media/chutes-14.jpg",
    "title": "CHUTES #14",
    "date": "2022",
    "dimensions_physical": "60 × 85 cm",
    "dimensions_pixels": {
      "width": 800,
      "height": 565
    },
    "series": ""
  },
  {
    "file": "media/chutes-15.jpg",
    "title": "CHUTES #15",
    "date": "2022",
    "dimensions_physical": "60 × 85 cm",
    "dimensions_pixels": {
      "width": 800,
      "height": 565
    },
    "series": ""
  },
  {
    "file": "media/chutes-16.jpg",
    "title": "CHUTES #16",
    "date": "2022",
    "dimensions_physical": "60 × 85 cm",
    "dimensions_pixels": {
      "width": 800,
      "height": 565
    },
    "series": ""
  },
  {
    "file": "media/chutes-17.jpg",
    "title": "CHUTES #17",
    "date": "2022",
    "dimensions_physical": "60 × 85 cm",
    "dimensions_pixels": {
      "width": 800,
      "height": 565
    },
    "series": ""
  },
  {
    "file": "media/chutes-18.jpg",
    "title": "CHUTES #18",
    "date": "2022",
    "dimensions_physical": "60 × 85 cm",
    "dimensions_pixels": {
      "width": 800,
      "height": 565
    },
    "series": ""
  },
  {
    "file": "media/chutes-19.jpg",
    "title": "CHUTES #19",
    "date": "2022",
    "dimensions_physical": "60 × 85 cm",
    "dimensions_pixels": {
      "width": 800,
      "height": 565
    },
    "series": ""
  },
  {
    "file": "media/chutes-20.jpg",
    "title": "CHUTES #20",
    "date": "2022",
    "dimensions_physical": "60 × 85 cm",
    "dimensions_pixels": {
      "width": 800,
      "height": 565
    },
    "series": ""
  },
  {
    "file": "media/chutes-21.jpg",
    "title": "CHUTES #21",
    "date": "2022",
    "dimensions_physical": "60 × 85 cm",
    "dimensions_pixels": {
      "width": 800,
      "height": 565
    },
    "series": ""
  },
  {
    "file": "media/chutes-22.jpg",
    "title": "CHUTES #22",
    "date": "2022",
    "dimensions_physical": "60 × 85 cm",
    "dimensions_pixels": {
      "width": 800,
      "height": 565
    },
    "series": ""
  }
]